snaql/__init__.py
snaql/convertors.py
snaql/factory.py
snaql/tests/__init__.py
snaql/tests/test_guards.py
snaql/tests/test_integration.py
snaql/tests/test_migrations.py
snaql/tests/test_schema.py
snaql/tests/test_usage.py
snaql-0.4.2.dist-info/LICENSE
snaql-0.4.2.dist-info/METADATA
snaql-0.4.2.dist-info/WHEEL
snaql-0.4.2.dist-info/top_level.txt
snaql-0.4.2.dist-info/RECORD
