Metadata-Version: 2.1
Name: snaql
Version: 0.4.2
Summary: Transparant *QL usage without ORM
Home-page: https://github.com/semirook/snaql
Author: Roman Zaiev
Author-email: semirook@gmail.com
License: MIT
Platform: UNKNOWN
Classifier: Development Status :: 5 - Production/Stable
Classifier: Intended Audience :: Developers
Classifier: License :: OSI Approved :: MIT License
Classifier: Operating System :: OS Independent
Classifier: Programming Language :: Python
Classifier: Programming Language :: Python :: 2.7
Classifier: Programming Language :: Python :: 3.5
Classifier: Programming Language :: Python :: 3.6
Classifier: Programming Language :: Python :: 3.7
Classifier: Topic :: Software Development :: Libraries :: Python Modules
Requires-Dist: Jinja2 (>=2.9.5)
Requires-Dist: schema (>=0.6.5)
